flask_lac/__init__.py
flask_lac/user.py
flask_lac-1.2.0.dist-info/METADATA
flask_lac-1.2.0.dist-info/WHEEL
flask_lac-1.2.0.dist-info/top_level.txt
flask_lac-1.2.0.dist-info/RECORD
