Metadata-Version: 2.1
Name: flask_lac
Version: 1.2.0
Summary: A simple authentication package for Flask applications
Home-page: https://github.com/botsarefuture/flask_lac
Author: Verso Vuorenmaa
Author-email: verso@luova.club
Classifier: Programming Language :: Python :: 3
Classifier: License :: OSI Approved :: MIT License
Classifier: Operating System :: OS Independent
Requires-Python: >=3.6
Requires-Dist: Flask >=1.1.2
Requires-Dist: Requests >=2.24.0
Requires-Dist: Werkzeug >=1.0.1
